MANIFEST.in
note_data.xml
note_demo.xml
note_view.xml
setup.py
./__init__.py
./__openerp__.py
./note.py
./tests/__init__.py
./tests/test_note.py
i18n/bs.po
i18n/cs.po
i18n/de.po
i18n/es.po
i18n/fr.po
i18n/hr.po
i18n/hu.po
i18n/id.po
i18n/it.po
i18n/lt.po
i18n/mk.po
i18n/mn.po
i18n/nl.po
i18n/note.pot
i18n/pl.po
i18n/pt.po
i18n/pt_BR.po
i18n/ro.po
i18n/ru.po
i18n/sl.po
i18n/sv.po
i18n/tr.po
i18n/zh_CN.po
images/categories_tree.jpeg
images/note.jpeg
images/note_kanban.jpeg
openerp_note.egg-info/PKG-INFO
openerp_note.egg-info/SOURCES.txt
openerp_note.egg-info/dependency_links.txt
openerp_note.egg-info/requires.txt
openerp_note.egg-info/top_level.txt
security/ir.model.access.csv
security/ir.rule.xml
security/note_security.xml
static/src/img/icon.png